Metadata-Version: 2.4
Name: iflow-mcp-ntk148v-alertmanager
Version: 1.1.0
Summary: MCP Server for Prometheus Alertmanager integration
Requires-Python: >=3.12
License-File: LICENSE
Requires-Dist: mcp[cli]>=1.8.1
Requires-Dist: requests>=2.32.3
Dynamic: license-file
